plover_merge_words/__init__.py
plover_merge_words/merge.py
plover_merge_words-0.1.1.dist-info/LICENSE.txt
plover_merge_words-0.1.1.dist-info/METADATA
plover_merge_words-0.1.1.dist-info/WHEEL
plover_merge_words-0.1.1.dist-info/entry_points.txt
plover_merge_words-0.1.1.dist-info/top_level.txt
plover_merge_words-0.1.1.dist-info/zip-safe
plover_merge_words-0.1.1.dist-info/RECORD
