Metadata-Version: 2.1
Name: plover-merge-words
Version: 0.1.1
Summary: Avoid repeating yourself or guarantee a space before a word.
Home-page: https://github.com/morinted/plover_merge_words
Author: Ted Morin
Author-email: morinted@gmail.com
License: GNU General Public License v3 or later (GPLv3+)
Keywords: plover plover_plugin
Platform: UNKNOWN
Classifier: Development Status :: 4 - Beta
Classifier: Environment :: Plugins
Classifier: Intended Audience :: End Users/Desktop
Classifier: License :: OSI Approved :: GNU General Public License v3 or later (GPLv3+)
Classifier: Operating System :: OS Independent
Classifier: Programming Language :: Python :: 3
Classifier: Programming Language :: Python :: 3.6
Requires-Dist: plover (>=4.0.0.dev7)
